piplus.py
setup.py
piplus.egg-info/PKG-INFO
piplus.egg-info/SOURCES.txt
piplus.egg-info/dependency_links.txt
piplus.egg-info/not-zip-safe
piplus.egg-info/requires.txt
piplus.egg-info/top_level.txt