Metadata-Version: 1.0
Name: piplus
Version: 0.1.1
Summary: Python Package Installer Plus
Home-page: https://github.com/daizhaolin/piplus
Author: daizhaolin
Author-email: UNKNOWN
License: BSD
Platform: 
